otium_common/__init__.py
otium_common/handlers/__init__.py
otium_common/handlers/handler.py
otium_common/interface/__init__.py
otium_common/interface/factory.py
otium_common/interface/repository.py
otium_common/repository/__init__.py
otium_common/repository/opensearch.py
otium_common/repository/redis.py
otium_common/serializers/response.py
otium_common/service/__init__.py
otium_common/service/aws.py
otium_common/service/kafka.py
otium_common/service/opensearch.py
otium_common/service/token.py
otium_common/token/__init__.py
otium_common/token/config.py
otium_common/token/payload.py
otium_common/token/token.py
otium_common/token/validator.py
otium_common/utills/__init__.py
otium_common/utills/enums.py
otium_common/utills/exception.py
otium_common/utills/id.py
otium_common/utills/response.py
otium_common/utills/time.py
otium_common/utills/types.py
otium_common-0.1.0.dist-info/METADATA
otium_common-0.1.0.dist-info/WHEEL
otium_common-0.1.0.dist-info/top_level.txt
otium_common-0.1.0.dist-info/RECORD
