Metadata-Version: 2.4
Name: otium-common
Version: 0.1.0
Author-email: 배주영 <bjs338570@gmail.com>
Project-URL: Repository, https://github.com/bjs3385/otium-common
Requires-Dist: djangorestframework<4.0.0,>=3.15.2
Requires-Dist: django==5.2b1
